keyneg/__init__.py
keyneg/_keyneg.py
keyneg/taxonomy.py
keyneg/utils.py
keyneg-1.1.0.dist-info/licenses/LICENSE
keyneg-1.1.0.dist-info/METADATA
keyneg-1.1.0.dist-info/WHEEL
keyneg-1.1.0.dist-info/top_level.txt
keyneg-1.1.0.dist-info/RECORD
