Metadata-Version: 2.4
Name: keyneg
Version: 1.1.0
Summary: A KeyBERT-style negative sentiment and keyword extractor for workforce intelligence and marketing analysis
Home-page: https://grandnasser.com
Author: Kaossara Osseni
Author-email: Kaossara Osseni <admin@grandnasser.com>
License-Expression: MIT
Project-URL: Homepage, https://github.com/Osseni94/keyneg
Project-URL: Documentation, https://github.com/Osseni94/keyneg#readme
Project-URL: Repository, https://github.com/Osseni94/keyneg
Project-URL: Issues, https://github.com/Osseni94/keyneg/issues
Keywords: nlp,sentiment-analysis,keyword-extraction,workforce-intelligence,text-analysis,negative-sentiment,keybert,sentence-transformers,employee-feedback,hr-analytics
Classifier: Development Status :: 4 - Beta
Classifier: Intended Audience :: Developers
Classifier: Intended Audience :: Science/Research
Classifier: Operating System :: OS Independent
Classifier: Programming Language :: Python :: 3
Classifier: Programming Language :: Python :: 3.8
Classifier: Programming Language :: Python :: 3.9
Classifier: Programming Language :: Python :: 3.10
Classifier: Programming Language :: Python :: 3.11
Classifier: Programming Language :: Python :: 3.12
Classifier: Topic :: Scientific/Engineering :: Artificial Intelligence
Classifier: Topic :: Text Processing :: Linguistic
Classifier: Topic :: Software Development :: Libraries :: Python Modules
Requires-Python: >=3.8
License-File: LICENSE
Requires-Dist: sentence-transformers>=2.2.0
Requires-Dist: scikit-learn>=1.0.0
Requires-Dist: numpy>=1.21.0
Provides-Extra: app
Requires-Dist: streamlit>=1.20.0; extra == "app"
Requires-Dist: pandas>=1.3.0; extra == "app"
Provides-Extra: dev
Requires-Dist: pytest>=7.0.0; extra == "dev"
Requires-Dist: pytest-cov>=4.0.0; extra == "dev"
Requires-Dist: black>=23.0.0; extra == "dev"
Requires-Dist: flake8>=6.0.0; extra == "dev"
Requires-Dist: twine>=4.0.0; extra == "dev"
Requires-Dist: build>=0.10.0; extra == "dev"
Provides-Extra: all
Requires-Dist: streamlit>=1.20.0; extra == "all"
Requires-Dist: pandas>=1.3.0; extra == "all"
Requires-Dist: transformers>=4.20.0; extra == "all"
Dynamic: author
Dynamic: home-page
Dynamic: license-file
Dynamic: requires-python
